LICENSE
setup.py
transcriber_service/__init__.py
transcriber_service.egg-info/PKG-INFO
transcriber_service.egg-info/SOURCES.txt
transcriber_service.egg-info/dependency_links.txt
transcriber_service.egg-info/not-zip-safe
transcriber_service.egg-info/requires.txt
transcriber_service.egg-info/top_level.txt
transcriber_service/application/__init__.py
transcriber_service/application/serialization/__init__.py
transcriber_service/application/serialization/audio_mapper.py
transcriber_service/application/serialization/entity_mapper_factory.py
transcriber_service/application/serialization/serializer_adapter.py
transcriber_service/application/serialization/storage_mapper.py
transcriber_service/application/serialization/user_mapper.py
transcriber_service/application/serialization/dto/__init__.py
transcriber_service/application/serialization/dto/audio_record_dto.py
transcriber_service/application/serialization/dto/storage_dto.py
transcriber_service/application/serialization/dto/user_dto.py
transcriber_service/application/services/__init__.py
transcriber_service/application/services/audio_service.py
transcriber_service/application/services/auth_service.py
transcriber_service/application/services/istorage_service.py
transcriber_service/application/services/storage_service.py
transcriber_service/application/services/user_service.py
transcriber_service/domain/__init__.py
transcriber_service/domain/exceptions.py
transcriber_service/domain/entities/__init__.py
transcriber_service/domain/entities/audio.py
transcriber_service/domain/entities/storage.py
transcriber_service/domain/entities/user.py
transcriber_service/domain/factories/__init__.py
transcriber_service/domain/factories/audio_factory.py
transcriber_service/domain/factories/storage_factory.py
transcriber_service/domain/factories/user_factory.py
transcriber_service/domain/interfaces/__init__.py
transcriber_service/domain/interfaces/entities/__init__.py
transcriber_service/domain/interfaces/entities/iaudio.py
transcriber_service/domain/interfaces/entities/imapper.py
transcriber_service/domain/interfaces/entities/istorage.py
transcriber_service/domain/interfaces/entities/iuser.py
transcriber_service/domain/interfaces/factories/__init__.py
